auth0login/__init__.py
auth0login/admin.py
auth0login/apps.py
auth0login/auth0backend.py
auth0login/models.py
auth0login/tests.py
auth0login/urls.py
auth0login/views.py
auth0login/migrations/__init__.py
network/__init__.py
network/_version.py
network/celery.py
network/settings.py
network/urls.py
network/wsgi.py
network/api/__init__.py
network/api/authentication.py
network/api/filters.py
network/api/pagination.py
network/api/perms.py
network/api/renderers.py
network/api/serializers.py
network/api/tests.py
network/api/throttling.py
network/api/urls.py
network/api/views.py
network/base/__init__.py
network/base/admin.py
network/base/apps.py
network/base/cache.py
network/base/context_processors.py
network/base/db_api.py
network/base/decorators.py
network/base/forms.py
network/base/managers.py
network/base/models.py
network/base/perms.py
network/base/rating_tasks.py
network/base/scheduling.py
network/base/serializers.py
network/base/signals.py
network/base/stats.py
network/base/tasks.py
network/base/test_orbital.py
network/base/test_utils.py
network/base/tests.py
network/base/urls.py
network/base/utils.py
network/base/validators.py
network/base/management/__init__.py
network/base/management/commands/__init__.py
network/base/management/commands/fetch_data.py
network/base/management/commands/initialize.py
network/base/management/commands/load_default_data.py
network/base/management/commands/update_station_last_seen.py
network/base/migrations/0001_initial.py
network/base/migrations/0002_auto_20151011_1406.py
network/base/migrations/0003_auto_20160119_1856.py
network/base/migrations/0004_station_horizon.py
network/base/migrations/0005_auto_20160320_1619.py
network/base/migrations/0006_auto_20160325_0126.py
network/base/migrations/0007_data_payload_demode.py
network/base/migrations/0008_auto_20160406_1605.py
network/base/migrations/0009_auto_20160506_0826.py
network/base/migrations/0010_auto_20160507_1550.py
network/base/migrations/0011_satellite_manual_tle.py
satnogs_network-1.123.dist-info/licenses/LICENSE
satnogs_network-1.123.dist-info/METADATA
satnogs_network-1.123.dist-info/WHEEL
satnogs_network-1.123.dist-info/top_level.txt
satnogs_network-1.123.dist-info/RECORD
